task3/counter.sv
//task 3.1:
/* module counter #(
    parameter WIDTH = 8
)(
    //interface signals
    input logic         clk,
    input logic         rst,
    input logic         ld,         //flag to load counter from data
    input logic [WIDTH-1:0] v,      //value to preload
    output logic [WIDTH-1:0] count
);


always_ff @ (posedge clk)
    if (rst) count <= {WIDTH{1'b0}};
    else     count <= ld ? count : count + {{WIDTH-1{1'b0}}, 1'b1};
endmodule */ 

//task 3.2:

module counter #(
    parameter WIDTH = 8
)(
    input  logic         clk,
    input  logic         rst,
    input  logic         ld,         // Vbuddy pushbutton
    input  logic [WIDTH-1:0] v,     // value to preload
    output logic [WIDTH-1:0] count
);

logic ld_d;  // delayed version of ld to detect edges

always_ff @(posedge clk) begin
    if (rst) begin
        count <= {WIDTH{1'b0}};
        ld_d   <= 0;
    end else begin
        ld_d <= ld; // store previous value
        // Increment only on rising edge of ld
        if (ld ^ ld_d) begin
            count <= count + 1;
        end
    end
end

endmodule

task3/counter.vcd
$version Generated by VerilatedVcd $end
$date Tue Oct 21 23:04:00 2025 $end
$timescale 1ps $end

 $scope module TOP $end
  $var wire  1 # clk $end
  $var wire  8 ' count [7:0] $end
  $var wire  1 % ld $end
  $var wire  1 $ rst $end
  $var wire  8 & v [7:0] $end
  $scope module counter $end
   $var wire 32 ) WIDTH [31:0] $end
   $var wire  1 # clk $end
   $var wire  8 ' count [7:0] $end
   $var wire  1 % ld $end
   $var wire  1 ( ld_d $end
   $var wire  1 $ rst $end
   $var wire  8 & v [7:0] $end
  $upscope $end
 $upscope $end
$enddefinitions $end


#0
1#
1$
0%
b00000000 &
b00000000 '
0(
b00000000000000000000000000001000 )
#1
0#
#2
1#
1%
b00110100 &
#3
0#
#4
1#
#5
0#
#6
1#
0$
#7
0#
#8
1#
b00000001 '
1(
#9
0#
#10
1#
#11
0#
#12
1#
#13
0#
#14
1#
#15
0#
#16
1#
#17
0#
#18
1#
#19
0#
#20
1#
#21
0#
#22
1#
#23
0#
#24
1#
#25
0#
#26
1#
#27
0#
#28
1#
#29
0#
#30
1#
#31
0#
#32
1#
#33
0#
#34
1#
#35
0#
#36
1#
#37
0#
#38
1#
#39
0#
#40
1#
#41
0#
#42
1#
0%
#43
0#
#44
1#
b00000010 '
0(
#45
0#
#46
1#
#47
0#
#48
1#
#49
0#
#50
1#
#51
0#
#52
1#
#53
0#
#54
1#
#55
0#
#56
1#
#57
0#
#58
1#
1%
#59
0#
#60
1#
b00000011 '
1(
